LICENSE.txt
MANIFEST.in
Makefile
README.md
pyproject.toml
requirements-dev.txt
requirements.txt
setup.cfg
setup.py
doc/Makefile
doc/conf.py
doc/index.rst
doc/_templates/class.rst
doc/sphinxext/docscrape.py
doc/sphinxext/docscrape_sphinx.py
doc/sphinxext/math_dollar.py
doc/sphinxext/numpydoc.py
examples/phantom.py
mrrt/__init__.py
mrrt.utils.egg-info/PKG-INFO
mrrt.utils.egg-info/SOURCES.txt
mrrt.utils.egg-info/dependency_links.txt
mrrt.utils.egg-info/requires.txt
mrrt.utils.egg-info/top_level.txt
mrrt/utils/__init__.py
mrrt/utils/_cupy.py
mrrt/utils/_fft.py
mrrt/utils/_hist.py
mrrt/utils/_masking.py
mrrt/utils/_misc.py
mrrt/utils/_phantom.py
mrrt/utils/_power_method.py
mrrt/utils/config.py
mrrt/utils/version.py
mrrt/utils/tests/test_cupy.py
mrrt/utils/tests/test_fft.py
mrrt/utils/tests/test_hist.py
mrrt/utils/tests/test_masking.py
mrrt/utils/tests/test_misc.py
mrrt/utils/tests/test_phantom.py
mrrt/utils/tests/test_power_method.py