Metadata-Version: 1.2
Name: mrrt.utils
Version: 0.2.2
Summary: mrrt.utils: common utilities supporting other mritools packages
Home-page: http://github.com/mritools/mrrt.utils
Author: Gregory R. Lee
Author-email: grlee77@gmail.com
Maintainer: Gregory R. Lee
Maintainer-email: grlee77@gmail.com
License: BSD
Platform: OS Independent
Classifier: Development Status :: 4 - Beta
Classifier: Environment :: Console
Classifier: Intended Audience :: Science/Research
Classifier: License :: OSI Approved :: BSD License
Classifier: Operating System :: OS Independent
Classifier: Programming Language :: Python
Classifier: Topic :: Scientific/Engineering
Requires: numpy
Requires: scipy
Requires-Python: >= 3.6
